imagedata_format_biff/__init__.py
imagedata_format_biff/biffplugin.py
imagedata_format_biff-0.0.4.dist-info/LICENSE.txt
imagedata_format_biff-0.0.4.dist-info/METADATA
imagedata_format_biff-0.0.4.dist-info/WHEEL
imagedata_format_biff-0.0.4.dist-info/entry_points.txt
imagedata_format_biff-0.0.4.dist-info/top_level.txt
imagedata_format_biff-0.0.4.dist-info/RECORD
