Metadata-Version: 2.1
Name: imagedata-format-biff
Version: 0.0.4
Summary: Imagedata format plugin for biff image data
Home-page: https://github.com/erling6232/imagedata_format_biff
Author: Erling Andersen
Author-email: Erling.Andersen@Helse-Bergen.NO
License: MIT
Project-URL: Documentation, https://imagedata.readthedocs.io
Project-URL: Source Code, https://github.com/erling6232/imagedata_format_biff
Keywords: python,medical,imaging,biff
Classifier: Programming Language :: Python :: 3
Classifier: Development Status :: 4 - Beta
Classifier: Environment :: Other Environment
Classifier: Intended Audience :: Developers
Classifier: Intended Audience :: Healthcare Industry
Classifier: Intended Audience :: Science/Research
Classifier: License :: OSI Approved :: MIT License
Classifier: Operating System :: OS Independent
Classifier: Topic :: Software Development :: Libraries :: Python Modules
Classifier: Topic :: Scientific/Engineering :: Medical Science Apps.
Requires-Python: <3.12,>=3.8
License-File: LICENSE.txt
Requires-Dist: imagedata >=3.2.0
